{
    "suggestion": {
        "keywords": [],
        "cities": []
    },
    "count": "107",
    "infocode": "10000",
    "pois": [
        {
            "parent": [],
            "distance": [],
            "keytag": "教学楼",
            "importance": [],
            "biz_ext": {
                "cost": [],
                "opentime2": [],
                "rating": [],
                "open_time": []
            },
            "type": "科教文化服务;学校;学校",
            "photos": [
                {
                    "title": [],
                    "url": "http://store.is.autonavi.com/showpic/677f170f77df0a279844d097dc5e45bf"
                },
                {
                    "title": [],
                    "url": "https://store.is.autonavi.com/showpic/5c3e18cb24b9b2bf121728c2ce7705ea"
                },
                {
                    "title": [],
                    "url": "http://store.is.autonavi.com/showpic/89f90190bc9730871d492eb26b7a1eed"
                }
            ],
            "building": [],
            "typecode": "141200",
            "shopinfo": "0",
            "poiweight": [],
            "adname": "新绛县",
            "featured_reviews_remake": [],
            "tel": [],
            "id": "B0GDJA4BBL",
            "address": "顺城街293号",
            "space_num": [],
            "pname": "山西省",
            "biz_type": [],
            "cityname": "运城市",
            "childtype": [],
            "atag": [],
            "name": "新纺学校",
            "location": "111.197015,35.591464",
            "shopid": [],
            "favorite_num": [],
            "featured_reviews": []
        },
        {
            "parent": [],
            "distance": [],
            "keytag": "中学",
            "importance": [],
            "biz_ext": {
                "cost": [],
                "opentime2": [],
                "rating": [],
                "open_time": []
            },
            "type": "科教文化服务;学校;中学",
            "photos": [
                {
                    "title": [],
                    "url": "https://aos-comment.amap.com/B0FFFEVRXR/comment/content_media_external_images_media_100000783_1742725372314_25203646.jpg"
                },
                {
                    "title": [],
                    "url": "https://aos-comment.amap.com/B0FFFEVRXR/comment/content_media_external_file_100003051_1761864146274_59967805.jpg"
                },
                {
                    "title": [],
                    "url": "https://aos-comment.amap.com/B0FFFEVRXR/comment/64054C8A_A3F6_4053_AF47_C7BF2FEA76D9_L0_001_2000_150_1757117118400_40883981.jpg"
                }
            ],
            "building": [],
            "typecode": "141202",
            "shopinfo": "0",
            "poiweight": [],
            "adname": "新绛县",
            "featured_reviews_remake": [],
            "tel": "0359-8791999",
            "id": "B0FFFEVRXR",
            "address": "迎宾路与荀子路交叉口西160米",
            "space_num": [],
            "pname": "山西省",
            "biz_type": [],
            "cityname": "运城市",
            "childtype": [],
            "atag": [],
            "name": "海泉中学",
            "location": "111.210933,35.629541",
            "shopid": [],
            "favorite_num": [],
            "featured_reviews": []
        },
        {
            "parent": "B0FFFEVRXR",
            "distance": [],
            "keytag": "高级中学",
            "importance": [],
            "biz_ext": {
                "cost": [],
                "opentime2": [],
                "rating": [],
                "open_time": []
            },
            "type": "科教文化服务;学校;中学",
            "photos": [
                {
                    "title": [],
                    "url": "https://store.is.autonavi.com/showpic/ba3b8ea22222f1a5fc500c2334011026"
                },
                {
                    "title": [],
                    "url": "http://store.is.autonavi.com/showpic/d3d4f808d3a6f6ffbfd85bcbfbf0b42a"
                },
                {
                    "title": [],
                    "url": "https://store.is.autonavi.com/showpic/d21a93c97ee5ee6e6803f2cddea680c6"
                }
            ],
            "building": [],
            "typecode": "141202",
            "shopinfo": "0",
            "poiweight": [],
            "adname": "新绛县",
            "featured_reviews_remake": [],
            "tel": [],
            "id": "B0FFIBIJIC",
            "address": "商品一条街",
            "space_num": [],
            "pname": "山西省",
            "biz_type": [],
            "cityname": "运城市",
            "childtype": "0",
            "atag": [],
            "name": "海泉学校(东校区)",
            "location": "111.211794,35.626832",
            "shopid": [],
            "favorite_num": [],
            "featured_reviews": []
        },
        {
            "parent": [],
            "distance": [],
            "keytag": "高级中学",
            "importance": [],
            "biz_ext": {
                "cost": [],
                "opentime2": [],
                "rating": [],
                "open_time": []
            },
            "type": "科教文化服务;学校;中学",
            "photos": [
                {
                    "title": [],
                    "url": "https://store.is.autonavi.com/showpic/c0cf4f5e1de4f9b442fe63da0bfa291a"
                },
                {
                    "title": [],
                    "url": "http://store.is.autonavi.com/showpic/b53d488d44272a61bcfa88ccff68841e"
                },
                {
                    "title": [],
                    "url": "http://store.is.autonavi.com/showpic/395fe0f8ba5ba9927771b037d1e94a7f"
                }
            ],
            "building": [],
            "typecode": "141202",
            "shopinfo": "0",
            "poiweight": [],
            "adname": "新绛县",
            "featured_reviews_remake": [],
            "tel": [],
            "id": "B0FFHXSMI0",
            "address": "峨眉路附近",
            "space_num": [],
            "pname": "山西省",
            "biz_type": [],
            "cityname": "运城市",
            "childtype": [],
            "atag": [],
            "name": "新绛中学",
            "location": "111.222277,35.642085",
            "shopid": [],
            "favorite_num": [],
            "featured_reviews": []
        },
        {
            "parent": [],
            "distance": [],
            "keytag": "中学",
            "importance": [],
            "biz_ext": {
                "cost": [],
                "opentime2": [],
                "rating": [],
                "open_time": []
            },
            "type": "科教文化服务;学校;中学",
            "photos": [
                {
                    "title": [],
                    "url": "http://store.is.autonavi.com/showpic/9e4579a4fa202782d4b2a19654aae91c"
                },
                {
                    "title": [],
                    "url": "http://store.is.autonavi.com/showpic/1704a4d3fb7f868c9f1fd0525576a6e7"
                },
                {
                    "title": [],
                    "url": "http://store.is.autonavi.com/showpic/1ece479a99b5312126508b525c25e640"
                }
            ],
            "building": [],
            "typecode": "141202",
            "shopinfo": "0",
            "poiweight": [],
            "adname": "新绛县",
            "featured_reviews_remake": [],
            "tel": [],
            "id": "B0FFIBFDR7",
            "address": [],
            "space_num": [],
            "pname": "山西省",
            "biz_type": [],
            "cityname": "运城市",
            "childtype": [],
            "atag": [],
            "name": "海泉学校",
            "location": "111.231487,35.615132",
            "shopid": [],
            "favorite_num": [],
            "featured_reviews": []
        },
        {
            "parent": [],
            "distance": [],
            "keytag": "初级中学",
            "importance": [],
            "biz_ext": {
                "cost": [],
                "opentime2": [],
                "rating": [],
                "open_time": []
            },
            "type": "科教文化服务;学校;小学",
            "photos": [
                {
                    "title": [],
                    "url": "http://store.is.autonavi.com/showpic/a90768c671764bc7f77f4f0d8325e7e3"
                },
                {
                    "title": [],
                    "url": "http://store.is.autonavi.com/showpic/f1051148808b96df8a5153f4c4e5e9f8"
                },
                {
                    "title": [],
                    "url": "http://store.is.autonavi.com/showpic/579a306e8a5906fb0fa140fad31af1d6"
                }
            ],
            "building": [],
            "typecode": "141203",
            "shopinfo": "0",
            "poiweight": [],
            "adname": "新绛县",
            "featured_reviews_remake": [],
            "tel": [],
            "id": "B0FFHTRGU8",
            "address": "荀子街与文体路交叉口西200米",
            "space_num": [],
            "pname": "山西省",
            "biz_type": [],
            "cityname": "运城市",
            "childtype": [],
            "atag": [],
            "name": "海泉学校(西校区)",
            "location": "111.206016,35.630485",
            "shopid": [],
            "favorite_num": [],
            "featured_reviews": []
        },
        {
            "parent": [],
            "distance": [],
            "keytag": "初级中学",
            "importance": [],
            "biz_ext": {
                "cost": [],
                "opentime2": [],
                "rating": [],
                "open_time": []
            },
            "type": "科教文化服务;学校;中学",
            "photos": [
                {
                    "title": [],
                    "url": "https://store.is.autonavi.com/showpic/74e492fe466fd1622460846fec174ed8"
                },
                {
                    "title": [],
                    "url": "https://store.is.autonavi.com/showpic/27c6db03a9c4920e3e716378d79a470a"
                },
                {
                    "title": [],
                    "url": "https://store.is.autonavi.com/showpic/9de6f7715668bcefe70bb7bfad6c94a9"
                }
            ],
            "building": [],
            "typecode": "141202",
            "shopinfo": "0",
            "poiweight": [],
            "adname": "新绛县",
            "featured_reviews_remake": [],
            "tel": "0359-7528703",
            "id": "B0FFHTRF9L",
            "address": "学府花园旁边",
            "space_num": [],
            "pname": "山西省",
            "biz_type": [],
            "cityname": "运城市",
            "childtype": [],
            "atag": [],
            "name": "新绛县第二中学",
            "location": "111.202969,35.628933",
            "shopid": [],
            "favorite_num": [],
            "featured_reviews": []
        },
        {
            "parent": [],
            "distance": [],
            "keytag": "小学",
            "importance": [],
            "biz_ext": {
                "cost": [],
                "opentime2": [],
                "rating": "4.6",
                "open_time": []
            },
            "type": "科教文化服务;学校;职业技术学校",
            "photos": [
                {
                    "title": [],
                    "url": "http://store.is.autonavi.com/showpic/8d5e790246192bb6b6897eb8052ccd66"
                },
                {
                    "title": [],
                    "url": "http://store.is.autonavi.com/showpic/ee09f68007ce55600212ece654a8159b"
                }
            ],
            "building": [],
            "typecode": "141206",
            "shopinfo": "0",
            "poiweight": [],
            "adname": "新绛县",
            "featured_reviews_remake": [],
            "tel": "13935965320",
            "id": "B01670MJTW",
            "address": "龙兴镇正平街95号",
            "space_num": [],
            "pname": "山西省",
            "biz_type": [],
            "cityname": "运城市",
            "childtype": [],
            "atag": [],
            "name": "新华学校",
            "location": "111.216482,35.617920",
            "shopid": [],
            "favorite_num": [],
            "featured_reviews": []
        },
        {
            "parent": "B01670MJTW",
            "distance": [],
            "keytag": "小学",
            "importance": [],
            "biz_ext": {
                "cost": [],
                "opentime2": [],
                "rating": [],
                "open_time": []
            },
            "type": "科教文化服务;学校;小学",
            "photos": [
                {
                    "title": [],
                    "url": "http://store.is.autonavi.com/showpic/53e3a43c6fa838e3346fe82de683ab67"
                },
                {
                    "title": [],
                    "url": "http://store.is.autonavi.com/showpic/3d16f85f787c833217e2edae9d66497e"
                },
                {
                    "title": [],
                    "url": "http://store.is.autonavi.com/showpic/52cc773966b073ab60ba0da0731fdd58"
                }
            ],
            "building": [],
            "typecode": "141203",
            "shopinfo": "1",
            "poiweight": [],
            "adname": "新绛县",
            "featured_reviews_remake": [],
            "tel": "0359-7526852",
            "id": "B0G1YSTSKW",
            "address": "内朝殿路49号",
            "space_num": [],
            "pname": "山西省",
            "biz_type": [],
            "cityname": "运城市",
            "childtype": "309",
            "atag": [],
            "name": "礼乐园新华学校小学部",
            "location": "111.220736,35.620132",
            "shopid": [],
            "favorite_num": [],
            "featured_reviews": []
        },
        {
            "parent": [],
            "distance": [],
            "keytag": "高级中学",
            "importance": [],
            "biz_ext": {
                "cost": [],
                "opentime2": [],
                "rating": [],
                "open_time": []
            },
            "type": "科教文化服务;学校;中学",
            "photos": [
                {
                    "title": [],
                    "url": "http://store.is.autonavi.com/showpic/cd90c7f40cb99b768f450c28062eb446"
                }
            ],
            "building": [],
            "typecode": "141202",
            "shopinfo": "0",
            "poiweight": [],
            "adname": "新绛县",
            "featured_reviews_remake": [],
            "tel": [],
            "id": "B0FFFEWAY4",
            "address": "新绛县文体路与011乡道交叉口南140米",
            "space_num": [],
            "pname": "山西省",
            "biz_type": [],
            "cityname": "运城市",
            "childtype": [],
            "atag": [],
            "name": "龙兴中学",
            "location": "111.206708,35.623353",
            "shopid": [],
            "favorite_num": [],
            "featured_reviews": []
        },
        {
            "parent": [],
            "distance": [],
            "keytag": "高级中学",
            "importance": [],
            "biz_ext": {
                "cost": [],
                "opentime2": [],
                "rating": "4.5",
                "open_time": []
            },
            "type": "科教文化服务;学校;职业技术学校",
            "photos": [
                {
                    "title": [],
                    "url": "http://store.is.autonavi.com/showpic/998bdff1c1dae5cae03480983a6df285"
                }
            ],
            "building": [],
            "typecode": "141206",
            "shopinfo": "0",
            "poiweight": [],
            "adname": "新绛县",
            "featured_reviews_remake": [],
            "tel": [],
            "id": "B0FFFEXZW1",
            "address": "东门街9号附近",
            "space_num": [],
            "pname": "山西省",
            "biz_type": [],
            "cityname": "运城市",
            "childtype": [],
            "atag": [],
            "name": "新绛县龙兴学校",
            "location": "111.231711,35.619113",
            "shopid": [],
            "favorite_num": [],
            "featured_reviews": []
        },
        {
            "parent": [],
            "distance": [],
            "keytag": "初级中学",
            "importance": [],
            "biz_ext": {
                "cost": [],
                "opentime2": [],
                "rating": [],
                "open_time": []
            },
            "type": "科教文化服务;学校;学校",
            "photos": [
                {
                    "title": [],
                    "url": "https://store.is.autonavi.com/showpic/27326c82531687476acf2efdff449ae4"
                },
                {
                    "title": [],
                    "url": "https://aos-comment.amap.com/B01670MV2Z/comment/content_media_external_file_100007158_1762498792679_78029572.jpg"
                },
                {
                    "title": [],
                    "url": "http://store.is.autonavi.com/showpic/d8a18043cd9c4a9de4bc7f40d8cc3568"
                }
            ],
            "building": [],
            "typecode": "141200",
            "shopinfo": "0",
            "poiweight": [],
            "adname": "新绛县",
            "featured_reviews_remake": [],
            "tel": [],
            "id": "B01670MV2Z",
            "address": "法院斜对面",
            "space_num": [],
            "pname": "山西省",
            "biz_type": [],
            "cityname": "运城市",
            "childtype": [],
            "atag": [],
            "name": "西关学校",
            "location": "111.211251,35.613742",
            "shopid": [],
            "favorite_num": [],
            "featured_reviews": []
        },
        {
            "parent": [],
            "distance": [],
            "keytag": "高级中学",
            "importance": [],
            "biz_ext": {
                "cost": [],
                "opentime2": [],
                "rating": [],
                "open_time": []
            },
            "type": "科教文化服务;学校;中学",
            "photos": [
                {
                    "title": [],
                    "url": "https://store.is.autonavi.com/showpic/33bf497958da0b0dcff3a0ca1336db1c"
                }
            ],
            "building": [],
            "typecode": "141202",
            "shopinfo": "0",
            "poiweight": [],
            "adname": "新绛县",
            "featured_reviews_remake": [],
            "tel": [],
            "id": "B01670MC4P",
            "address": "108国道",
            "space_num": [],
            "pname": "山西省",
            "biz_type": [],
            "cityname": "运城市",
            "childtype": [],
            "atag": [],
            "name": "新绛汾河中学",
            "location": "111.244077,35.599989",
            "shopid": [],
            "favorite_num": [],
            "featured_reviews": []
        },
        {
            "parent": [],
            "distance": [],
            "keytag": "小学",
            "importance": [],
            "biz_ext": {
                "cost": [],
                "opentime2": [],
                "rating": [],
                "open_time": []
            },
            "type": "科教文化服务;学校;中学",
            "photos": [
                {
                    "title": [],
                    "url": "http://store.is.autonavi.com/showpic/df77d207d332c60b1aaece7c62a7f5d8"
                },
                {
                    "title": [],
                    "url": "https://store.is.autonavi.com/showpic/fff422b936b38efbf77adfd2081e28dd"
                }
            ],
            "building": [],
            "typecode": "141202",
            "shopinfo": "0",
            "poiweight": [],
            "adname": "新绛县",
            "featured_reviews_remake": [],
            "tel": [],
            "id": "B0FFHFKD87",
            "address": "社区办新绛县东街",
            "space_num": [],
            "pname": "山西省",
            "biz_type": [],
            "cityname": "运城市",
            "childtype": [],
            "atag": [],
            "name": "东街逸夫学校",
            "location": "111.228658,35.615354",
            "shopid": [],
            "favorite_num": [],
            "featured_reviews": []
        },
        {
            "parent": [],
            "distance": [],
            "keytag": "高级中学",
            "importance": [],
            "biz_ext": {
                "cost": [],
                "opentime2": [],
                "rating": [],
                "open_time": []
            },
            "type": "科教文化服务;学校;中学",
            "photos": [
                {
                    "title": [],
                    "url": "http://store.is.autonavi.com/showpic/8e5315d3b727147234b6ef45320c82c8"
                }
            ],
            "building": [],
            "typecode": "141202",
            "shopinfo": "0",
            "poiweight": [],
            "adname": "新绛县",
            "featured_reviews_remake": [],
            "tel": [],
            "id": "B01670020N",
            "address": "古交镇",
            "space_num": [],
            "pname": "山西省",
            "biz_type": [],
            "cityname": "运城市",
            "childtype": [],
            "atag": [],
            "name": "新绛县古交中学",
            "location": "111.147261,35.614252",
            "shopid": [],
            "favorite_num": [],
            "featured_reviews": []
        },
        {
            "parent": [],
            "distance": [],
            "keytag": "初级中学",
            "importance": [],
            "biz_ext": {
                "cost": [],
                "opentime2": [],
                "rating": [],
                "open_time": []
            },
            "type": "科教文化服务;学校;学校",
            "photos": [
                {
                    "title": [],
                    "url": "http://store.is.autonavi.com/showpic/0601aafd46085e007c7885fac38b088a"
                }
            ],
            "building": [],
            "typecode": "141200",
            "shopinfo": "0",
            "poiweight": [],
            "adname": "新绛县",
            "featured_reviews_remake": [],
            "tel": [],
            "id": "B01670M5SG",
            "address": "三泉镇三泉村路口",
            "space_num": [],
            "pname": "山西省",
            "biz_type": [],
            "cityname": "运城市",
            "childtype": [],
            "atag": [],
            "name": "育英学校",
            "location": "111.184233,35.681783",
            "shopid": [],
            "favorite_num": [],
            "featured_reviews": []
        },
        {
            "parent": [],
            "distance": [],
            "keytag": "中学",
            "importance": [],
            "biz_ext": {
                "cost": [],
                "opentime2": [],
                "rating": [],
                "open_time": []
            },
            "type": "科教文化服务;学校;中学",
            "photos": [
                {
                    "title": [],
                    "url": "http://store.is.autonavi.com/showpic/553dc2bd55a36572389e071200a97a2e"
                }
            ],
            "building": [],
            "typecode": "141202",
            "shopinfo": "0",
            "poiweight": [],
            "adname": "新绛县",
            "featured_reviews_remake": [],
            "tel": [],
            "id": "B0FFFEW3QI",
            "address": "龙兴镇庄儿头华新线希望学校",
            "space_num": [],
            "pname": "山西省",
            "biz_type": [],
            "cityname": "运城市",
            "childtype": [],
            "atag": [],
            "name": "新绛县希望学校",
            "location": "111.208890,35.626805",
            "shopid": [],
            "favorite_num": [],
            "featured_reviews": []
        },
        {
            "parent": [],
            "distance": [],
            "keytag": "小学",
            "importance": [],
            "biz_ext": {
                "cost": [],
                "opentime2": [],
                "rating": [],
                "open_time": []
            },
            "type": "科教文化服务;学校;中学",
            "photos": [
                {
                    "title": [],
                    "url": "http://store.is.autonavi.com/showpic/0aef5aef97b17e32c5d2773130df9096"
                }
            ],
            "building": [],
            "typecode": "141202",
            "shopinfo": "0",
            "poiweight": [],
            "adname": "新绛县",
            "featured_reviews_remake": [],
            "tel": [],
            "id": "B01670MOWZ",
            "address": "030乡道与039乡道交叉口西340米",
            "space_num": [],
            "pname": "山西省",
            "biz_type": [],
            "cityname": "运城市",
            "childtype": [],
            "atag": [],
            "name": "席村学校",
            "location": "111.168858,35.650168",
            "shopid": [],
            "favorite_num": [],
            "featured_reviews": []
        },
        {
            "parent": [],
            "distance": [],
            "keytag": "初级中学",
            "importance": [],
            "biz_ext": {
                "cost": [],
                "opentime2": [],
                "rating": [],
                "open_time": []
            },
            "type": "科教文化服务;学校;中学",
            "photos": [
                {
                    "title": [],
                    "url": "http://store.is.autonavi.com/showpic/3db63a7093b35087179a5f926d5fc5db"
                },
                {
                    "title": [],
                    "url": "http://store.is.autonavi.com/showpic/eb6e1febc1d0574eed90503f8c8cec57"
                }
            ],
            "building": [],
            "typecode": "141202",
            "shopinfo": "0",
            "poiweight": [],
            "adname": "新绛县",
            "featured_reviews_remake": [],
            "tel": [],
            "id": "B01670MV6S",
            "address": "北张镇泽古线青少年业余体校",
            "space_num": [],
            "pname": "山西省",
            "biz_type": [],
            "cityname": "运城市",
            "childtype": [],
            "atag": [],
            "name": "北张中学",
            "location": "111.109685,35.705286",
            "shopid": [],
            "favorite_num": [],
            "featured_reviews": []
        },
        {
            "parent": [],
            "distance": [],
            "keytag": "小学",
            "importance": [],
            "biz_ext": {
                "cost": [],
                "opentime2": [],
                "rating": [],
                "open_time": []
            },
            "type": "科教文化服务;学校;小学",
            "photos": [
                {
                    "title": [],
                    "url": "http://store.is.autonavi.com/showpic/3652b0e9abd0fdf9c968501abca6127d"
                }
            ],
            "building": [],
            "typecode": "141203",
            "shopinfo": "0",
            "poiweight": [],
            "adname": "新绛县",
            "featured_reviews_remake": [],
            "tel": [],
            "id": "B016700K0Z",
            "address": "横桥镇108国道",
            "space_num": [],
            "pname": "山西省",
            "biz_type": [],
            "cityname": "运城市",
            "childtype": [],
            "atag": [],
            "name": "狄庄学校",
            "location": "111.259254,35.599636",
            "shopid": [],
            "favorite_num": [],
            "featured_reviews": []
        },
        {
            "parent": [],
            "distance": [],
            "keytag": "初级中学",
            "importance": [],
            "biz_ext": {
                "cost": [],
                "opentime2": [],
                "rating": [],
                "open_time": []
            },
            "type": "科教文化服务;学校;中学",
            "photos": [
                {
                    "title": [],
                    "url": "https://store.is.autonavi.com/showpic/0757489314c88c2400a2242ed7787325"
                },
                {
                    "title": [],
                    "url": "https://store.is.autonavi.com/showpic/f32ee6ad9f3dcb114ae445598e10e836"
                },
                {
                    "title": [],
                    "url": "https://store.is.autonavi.com/showpic/37983b5029112abca4ac0c0dcaf2c8f5"
                }
            ],
            "building": [],
            "typecode": "141202",
            "shopinfo": "0",
            "poiweight": [],
            "adname": "新绛县",
            "featured_reviews_remake": [],
            "tel": [],
            "id": "B01670MB7E",
            "address": "东门街165号",
            "space_num": [],
            "pname": "山西省",
            "biz_type": [],
            "cityname": "运城市",
            "childtype": [],
            "atag": [],
            "name": "新绛县东城学校",
            "location": "111.237261,35.615400",
            "shopid": [],
            "favorite_num": [],
            "featured_reviews": []
        },
        {
            "parent": [],
            "distance": [],
            "keytag": "小学",
            "importance": [],
            "biz_ext": {
                "cost": [],
                "opentime2": [],
                "rating": [],
                "open_time": []
            },
            "type": "科教文化服务;学校;小学",
            "photos": [
                {
                    "title": [],
                    "url": "https://store.is.autonavi.com/showpic/0c15d032c5b0ee546e6efb74717745b2"
                },
                {
                    "title": [],
                    "url": "http://store.is.autonavi.com/showpic/1d062344801d3b18210858bb89f08d41"
                },
                {
                    "title": [],
                    "url": "http://store.is.autonavi.com/showpic/1424a2ce373a5baf4d2dc737ca9db712"
                }
            ],
            "building": [],
            "typecode": "141203",
            "shopinfo": "0",
            "poiweight": [],
            "adname": "新绛县",
            "featured_reviews_remake": [],
            "tel": [],
            "id": "B01670MP2F",
            "address": "三泉镇三泉村",
            "space_num": [],
            "pname": "山西省",
            "biz_type": [],
            "cityname": "运城市",
            "childtype": [],
            "atag": [],
            "name": "新绛县三泉镇三泉学校",
            "location": "111.161058,35.676164",
            "shopid": [],
            "favorite_num": [],
            "featured_reviews": []
        },
        {
            "parent": [],
            "distance": [],
            "keytag": "特殊需求教育",
            "importance": [],
            "biz_ext": {
                "cost": [],
                "opentime2": [],
                "rating": [],
                "open_time": []
            },
            "type": "科教文化服务;学校;学校",
            "photos": [
                {
                    "title": [],
                    "url": "http://store.is.autonavi.com/showpic/c407415e1e1dfe9ff106581f0f082932"
                },
                {
                    "title": [],
                    "url": "http://store.is.autonavi.com/showpic/5a08f2dc41db2473822072f8f4f9017e"
                },
                {
                    "title": [],
                    "url": "http://store.is.autonavi.com/showpic/e91c80697975212e96fead261dd7e381"
                }
            ],
            "building": [],
            "typecode": "141200",
            "shopinfo": "0",
            "poiweight": [],
            "adname": "新绛县",
            "featured_reviews_remake": [],
            "tel": [],
            "id": "B0FFF3VV7W",
            "address": "教育局教研室",
            "space_num": [],
            "pname": "山西省",
            "biz_type": [],
            "cityname": "运城市",
            "childtype": [],
            "atag": [],
            "name": "新绛县特殊教育学校",
            "location": "111.203776,35.623760",
            "shopid": [],
            "favorite_num": [],
            "featured_reviews": []
        },
        {
            "parent": [],
            "distance": [],
            "keytag": "小学",
            "importance": [],
            "biz_ext": {
                "cost": [],
                "opentime2": [],
                "rating": [],
                "open_time": []
            },
            "type": "科教文化服务;学校;学校",
            "photos": [
                {
                    "title": [],
                    "url": "http://store.is.autonavi.com/showpic/7fc474c73cabf7c87764d26c49897f53"
                }
            ],
            "building": [],
            "typecode": "141200",
            "shopinfo": "0",
            "poiweight": [],
            "adname": "新绛县",
            "featured_reviews_remake": [],
            "tel": [],
            "id": "B01670MOSN",
            "address": "万安镇万安村",
            "space_num": [],
            "pname": "山西省",
            "biz_type": [],
            "cityname": "运城市",
            "childtype": [],
            "atag": [],
            "name": "万安学校",
            "location": "111.136945,35.542889",
            "shopid": [],
            "favorite_num": [],
            "featured_reviews": []
        },
        {
            "parent": [],
            "distance": [],
            "keytag": "初级中学",
            "importance": [],
            "biz_ext": {
                "cost": [],
                "opentime2": [],
                "rating": [],
                "open_time": []
            },
            "type": "科教文化服务;学校;小学|科教文化服务;学校;中学",
            "photos": [
                {
                    "title": [],
                    "url": "http://store.is.autonavi.com/showpic/17a97790dc435f0ca54465ac35c62f8b"
                },
                {
                    "title": [],
                    "url": "http://store.is.autonavi.com/showpic/7cdc90b1bb1bda270885b3eb326e9d5b"
                }
            ],
            "building": [],
            "typecode": "141203|141202",
            "shopinfo": "0",
            "poiweight": [],
            "adname": "新绛县",
            "featured_reviews_remake": [],
            "tel": [],
            "id": "B0G1NL7326",
            "address": "北张镇泽古线北张示范小学",
            "space_num": [],
            "pname": "山西省",
            "biz_type": [],
            "cityname": "运城市",
            "childtype": [],
            "atag": [],
            "name": "新绛县北张学校",
            "location": "111.111050,35.707684",
            "shopid": [],
            "favorite_num": [],
            "featured_reviews": []
        },
        {
            "parent": [],
            "distance": [],
            "keytag": "初级中学",
            "importance": [],
            "biz_ext": {
                "cost": [],
                "opentime2": [],
                "rating": [],
                "open_time": []
            },
            "type": "科教文化服务;学校;学校",
            "photos": [
                {
                    "title": [],
                    "url": "http://store.is.autonavi.com/showpic/10a537bb1664044e422f23df8b5e1cbd"
                },
                {
                    "title": [],
                    "url": "http://store.is.autonavi.com/showpic/9cd2725030246e38cc7ee63391450076"
                },
                {
                    "title": [],
                    "url": "http://store.is.autonavi.com/showpic/482d446a44c2162bfbe0940b62eb0d91"
                }
            ],
            "building": [],
            "typecode": "141200",
            "shopinfo": "0",
            "poiweight": [],
            "adname": "新绛县",
            "featured_reviews_remake": [],
            "tel": [],
            "id": "B01670MP2L",
            "address": "039乡道南50米",
            "space_num": [],
            "pname": "山西省",
            "biz_type": [],
            "cityname": "运城市",
            "childtype": [],
            "atag": [],
            "name": "新绛县三泉镇水西学校",
            "location": "111.186620,35.639211",
            "shopid": [],
            "favorite_num": [],
            "featured_reviews": []
        },
        {
            "parent": [],
            "distance": [],
            "keytag": "初级中学",
            "importance": [],
            "biz_ext": {
                "cost": [],
                "opentime2": [],
                "rating": [],
                "open_time": []
            },
            "type": "科教文化服务;科教文化场所;科教文化场所",
            "photos": [
                {
                    "title": [],
                    "url": "http://store.is.autonavi.com/showpic/cd3dd0997e865ea726563d1929dfd496"
                }
            ],
            "building": [],
            "typecode": "140000",
            "shopinfo": "0",
            "poiweight": [],
            "adname": "新绛县",
            "featured_reviews_remake": [],
            "tel": [],
            "id": "B01670MYBT",
            "address": "龙兴镇娄庄村",
            "space_num": [],
            "pname": "山西省",
            "biz_type": [],
            "cityname": "运城市",
            "childtype": [],
            "atag": [],
            "name": "娄庄学校",
            "location": "111.264938,35.639796",
            "shopid": [],
            "favorite_num": [],
            "featured_reviews": []
        },
        {
            "parent": [],
            "distance": [],
            "keytag": "中学",
            "importance": [],
            "biz_ext": {
                "cost": [],
                "opentime2": [],
                "rating": [],
                "open_time": []
            },
            "type": "科教文化服务;学校;中学",
            "photos": [
                {
                    "title": [],
                    "url": "http://store.is.autonavi.com/showpic/e5ac31086c06415575edd799e27e5c35"
                }
            ],
            "building": [],
            "typecode": "141202",
            "shopinfo": "0",
            "poiweight": [],
            "adname": "新绛县",
            "featured_reviews_remake": [],
            "tel": [],
            "id": "B0167001ZW",
            "address": "泉掌镇泽古线泉掌中学",
            "space_num": [],
            "pname": "山西省",
            "biz_type": [],
            "cityname": "运城市",
            "childtype": [],
            "atag": [],
            "name": "新绛县泉掌中学",
            "location": "111.107930,35.660052",
            "shopid": [],
            "favorite_num": [],
            "featured_reviews": []
        },
        {
            "parent": [],
            "distance": [],
            "keytag": "小学",
            "importance": [],
            "biz_ext": {
                "cost": [],
                "opentime2": [],
                "rating": [],
                "open_time": []
            },
            "type": "科教文化服务;学校;小学",
            "photos": [
                {
                    "title": [],
                    "url": "http://store.is.autonavi.com/showpic/f475524b71c7365087cc03f6dbabff8c"
                }
            ],
            "building": [],
            "typecode": "141203",
            "shopinfo": "0",
            "poiweight": [],
            "adname": "新绛县",
            "featured_reviews_remake": [],
            "tel": [],
            "id": "B01670MJU6",
            "address": "南关村044号",
            "space_num": [],
            "pname": "山西省",
            "biz_type": [],
            "cityname": "运城市",
            "childtype": [],
            "atag": [],
            "name": "南关学校",
            "location": "111.228237,35.601169",
            "shopid": [],
            "favorite_num": [],
            "featured_reviews": []
        },
        {
            "parent": [],
            "distance": [],
            "keytag": "中学",
            "importance": [],
            "biz_ext": {
                "cost": [],
                "opentime2": [],
                "rating": [],
                "open_time": []
            },
            "type": "科教文化服务;学校;中学",
            "photos": [
                {
                    "title": [],
                    "url": "https://store.is.autonavi.com/showpic/b7aaede5dfa75dd80000002449864321"
                }
            ],
            "building": [],
            "typecode": "141202",
            "shopinfo": "0",
            "poiweight": [],
            "adname": "新绛县",
            "featured_reviews_remake": [],
            "tel": [],
            "id": "B0FFHEJM9K",
            "address": "阳王村",
            "space_num": [],
            "pname": "山西省",
            "biz_type": [],
            "cityname": "运城市",
            "childtype": [],
            "atag": [],
            "name": "阳王中学",
            "location": "111.127257,35.508969",
            "shopid": [],
            "favorite_num": [],
            "featured_reviews": []
        },
        {
            "parent": [],
            "distance": [],
            "keytag": "初级中学",
            "importance": [],
            "biz_ext": {
                "cost": [],
                "opentime2": [],
                "rating": [],
                "open_time": []
            },
            "type": "科教文化服务;学校;学校",
            "photos": [
                {
                    "title": [],
                    "url": "http://store.is.autonavi.com/showpic/cc3c69e126266d81e000926113c07182"
                },
                {
                    "title": [],
                    "url": "https://store.is.autonavi.com/showpic/7b79da44af82111c19d8c8a691f981d3"
                }
            ],
            "building": [],
            "typecode": "141200",
            "shopinfo": "0",
            "poiweight": [],
            "adname": "新绛县",
            "featured_reviews_remake": [],
            "tel": [],
            "id": "B016700GCH",
            "address": "清泽线与799县道交叉口北500米",
            "space_num": [],
            "pname": "山西省",
            "biz_type": [],
            "cityname": "运城市",
            "childtype": [],
            "atag": [],
            "name": "新绛县光村学校",
            "location": "111.175739,35.752984",
            "shopid": [],
            "favorite_num": [],
            "featured_reviews": []
        },
        {
            "parent": [],
            "distance": [],
            "keytag": "初级中学",
            "importance": [],
            "biz_ext": {
                "cost": [],
                "opentime2": [],
                "rating": [],
                "open_time": []
            },
            "type": "科教文化服务;科教文化场所;科教文化场所",
            "photos": [
                {
                    "title": [],
                    "url": "http://store.is.autonavi.com/showpic/620b3ad3307fcfaa4d191f88d1bbe857"
                }
            ],
            "building": [],
            "typecode": "140000",
            "shopinfo": "0",
            "poiweight": [],
            "adname": "新绛县",
            "featured_reviews_remake": [],
            "tel": [],
            "id": "B0FFKN5JGN",
            "address": "古交镇",
            "space_num": [],
            "pname": "山西省",
            "biz_type": [],
            "cityname": "运城市",
            "childtype": [],
            "atag": [],
            "name": "新绛县龙泉学校",
            "location": "111.170430,35.614517",
            "shopid": [],
            "favorite_num": [],
            "featured_reviews": []
        },
        {
            "parent": [],
            "distance": [],
            "keytag": "初级中学",
            "importance": [],
            "biz_ext": {
                "cost": [],
                "opentime2": [],
                "rating": [],
                "open_time": []
            },
            "type": "科教文化服务;学校;中学",
            "photos": [
                {
                    "title": [],
                    "url": "http://store.is.autonavi.com/showpic/39b0d600405dff6f3e2957686386f835"
                }
            ],
            "building": [],
            "typecode": "141202",
            "shopinfo": "0",
            "poiweight": [],
            "adname": "新绛县",
            "featured_reviews_remake": [],
            "tel": [],
            "id": "B0FFF4HHVS",
            "address": "泽掌镇泽掌村",
            "space_num": [],
            "pname": "山西省",
            "biz_type": [],
            "cityname": "运城市",
            "childtype": [],
            "atag": [],
            "name": "泽掌中学",
            "location": "111.166490,35.714746",
            "shopid": [],
            "favorite_num": [],
            "featured_reviews": []
        },
        {
            "parent": [],
            "distance": [],
            "keytag": "小学",
            "importance": [],
            "biz_ext": {
                "cost": [],
                "opentime2": [],
                "rating": [],
                "open_time": []
            },
            "type": "科教文化服务;学校;学校",
            "photos": [
                {
                    "title": [],
                    "url": "http://store.is.autonavi.com/showpic/d190049f982b1b9b154d345da9778924"
                }
            ],
            "building": [],
            "typecode": "141200",
            "shopinfo": "0",
            "poiweight": [],
            "adname": "新绛县",
            "featured_reviews_remake": [],
            "tel": [],
            "id": "B0FFLP4CLF",
            "address": "古交镇周流村",
            "space_num": [],
            "pname": "山西省",
            "biz_type": [],
            "cityname": "运城市",
            "childtype": [],
            "atag": [],
            "name": "新绛县古交镇周流学校",
            "location": "111.112139,35.600658",
            "shopid": [],
            "favorite_num": [],
            "featured_reviews": []
        },
        {
            "parent": [],
            "distance": [],
            "keytag": "小学",
            "importance": [],
            "biz_ext": {
                "cost": [],
                "opentime2": [],
                "rating": [],
                "open_time": []
            },
            "type": "科教文化服务;学校;学校",
            "photos": [
                {
                    "title": [],
                    "url": "http://store.is.autonavi.com/showpic/7d3c1e608a901b7f60f9849585c22da2"
                },
                {
                    "title": [],
                    "url": "http://store.is.autonavi.com/showpic/beb7d1af36049f42192b51625c4b9673"
                },
                {
                    "title": [],
                    "url": "http://store.is.autonavi.com/showpic/969adab063aeada902be7e2091409078"
                }
            ],
            "building": [],
            "typecode": "141200",
            "shopinfo": "0",
            "poiweight": [],
            "adname": "新绛县",
            "featured_reviews_remake": [],
            "tel": [],
            "id": "B0FFKKWABW",
            "address": "龙兴镇店头村店头",
            "space_num": [],
            "pname": "山西省",
            "biz_type": [],
            "cityname": "运城市",
            "childtype": [],
            "atag": [],
            "name": "店头寄宿制学校",
            "location": "111.279158,35.668004",
            "shopid": [],
            "favorite_num": [],
            "featured_reviews": []
        },
        {
            "parent": [],
            "distance": [],
            "keytag": "初级中学",
            "importance": [],
            "biz_ext": {
                "cost": [],
                "opentime2": [],
                "rating": [],
                "open_time": []
            },
            "type": "科教文化服务;学校;学校",
            "photos": [
                {
                    "title": [],
                    "url": "http://store.is.autonavi.com/showpic/aea0d1fb9677b2564496e2c4039d758e"
                }
            ],
            "building": [],
            "typecode": "141200",
            "shopinfo": "0",
            "poiweight": [],
            "adname": "新绛县",
            "featured_reviews_remake": [],
            "tel": [],
            "id": "B0FFGKQH2K",
            "address": "横桥乡",
            "space_num": [],
            "pname": "山西省",
            "biz_type": [],
            "cityname": "运城市",
            "childtype": [],
            "atag": [],
            "name": "符村学校",
            "location": "111.226492,35.564668",
            "shopid": [],
            "favorite_num": [],
            "featured_reviews": []
        },
        {
            "parent": [],
            "distance": [],
            "keytag": "小学",
            "importance": [],
            "biz_ext": {
                "cost": [],
                "opentime2": [],
                "rating": [],
                "open_time": []
            },
            "type": "科教文化服务;学校;学校",
            "photos": [],
            "building": [],
            "typecode": "141200",
            "shopinfo": "0",
            "poiweight": [],
            "adname": "新绛县",
            "featured_reviews_remake": [],
            "tel": [],
            "id": "B0FFM485I0",
            "address": [],
            "space_num": [],
            "pname": "山西省",
            "biz_type": [],
            "cityname": "运城市",
            "childtype": [],
            "atag": [],
            "name": "北王马学校",
            "location": "111.189321,35.628704",
            "shopid": [],
            "favorite_num": [],
            "featured_reviews": []
        },
        {
            "parent": [],
            "distance": [],
            "keytag": "初级中学",
            "importance": [],
            "biz_ext": {
                "cost": [],
                "opentime2": [],
                "rating": [],
                "open_time": []
            },
            "type": "科教文化服务;科教文化场所;科教文化场所",
            "photos": [
                {
                    "title": [],
                    "url": "http://store.is.autonavi.com/showpic/df2d8dbafbe8db349bf2dc48ccecf8ae"
                }
            ],
            "building": [],
            "typecode": "140000",
            "shopinfo": "0",
            "poiweight": [],
            "adname": "新绛县",
            "featured_reviews_remake": [],
            "tel": [],
            "id": "B0FFJ562DT",
            "address": [],
            "space_num": [],
            "pname": "山西省",
            "biz_type": [],
            "cityname": "运城市",
            "childtype": [],
            "atag": [],
            "name": "东薛郭学校",
            "location": "111.127634,35.642854",
            "shopid": [],
            "favorite_num": [],
            "featured_reviews": []
        },
        {
            "parent": [],
            "distance": [],
            "keytag": "初级中学",
            "importance": [],
            "biz_ext": {
                "cost": [],
                "opentime2": [],
                "rating": [],
                "open_time": []
            },
            "type": "科教文化服务;学校;中学",
            "photos": [
                {
                    "title": [],
                    "url": "http://store.is.autonavi.com/showpic/d8b5b5e7b2b4d022114969c139433b46"
                }
            ],
            "building": [],
            "typecode": "141202",
            "shopinfo": "0",
            "poiweight": [],
            "adname": "新绛县",
            "featured_reviews_remake": [],
            "tel": [],
            "id": "B0FFL5MWCE",
            "address": "临夏线1号",
            "space_num": [],
            "pname": "山西省",
            "biz_type": [],
            "cityname": "运城市",
            "childtype": [],
            "atag": [],
            "name": "横桥中学",
            "location": "111.231625,35.575425",
            "shopid": [],
            "favorite_num": [],
            "featured_reviews": []
        },
        {
            "parent": [],
            "distance": [],
            "keytag": "小学",
            "importance": [],
            "biz_ext": {
                "cost": [],
                "opentime2": [],
                "rating": [],
                "open_time": []
            },
            "type": "科教文化服务;科教文化场所;科教文化场所",
            "photos": [
                {
                    "title": [],
                    "url": "http://aos-cdn-image.amap.com/sns/ugccomment/a326b0cc-0424-499f-afd8-903814195d3a.jpg"
                }
            ],
            "building": [],
            "typecode": "140000",
            "shopinfo": "0",
            "poiweight": [],
            "adname": "新绛县",
            "featured_reviews_remake": [],
            "tel": [],
            "id": "B01670MOIP",
            "address": "古交镇",
            "space_num": [],
            "pname": "山西省",
            "biz_type": [],
            "cityname": "运城市",
            "childtype": [],
            "atag": [],
            "name": "王村学校",
            "location": "111.174278,35.575680",
            "shopid": [],
            "favorite_num": [],
            "featured_reviews": []
        },
        {
            "parent": [],
            "distance": [],
            "keytag": "幼儿园",
            "importance": [],
            "biz_ext": {
                "cost": [],
                "opentime2": [],
                "rating": [],
                "open_time": []
            },
            "type": "科教文化服务;学校;幼儿园",
            "photos": [
                {
                    "title": [],
                    "url": "https://store.is.autonavi.com/showpic/c1a8d5b439a79bbde1d4793d535cdce8"
                },
                {
                    "title": [],
                    "url": "http://store.is.autonavi.com/showpic/bfb3d6dd7ec3fdd39e45e62150dd9399"
                },
                {
                    "title": [],
                    "url": "https://store.is.autonavi.com/showpic/94643a69c80c7e330000002478216063?type=pic"
                }
            ],
            "building": [],
            "typecode": "141204",
            "shopinfo": "0",
            "poiweight": [],
            "adname": "新绛县",
            "featured_reviews_remake": [],
            "tel": [],
            "id": "B0I3USM02B",
            "address": "绛州大道与市府大道交叉口北320米",
            "space_num": [],
            "pname": "山西省",
            "biz_type": [],
            "cityname": "运城市",
            "childtype": [],
            "atag": [],
            "name": "新绛县新城幼儿园",
            "location": "111.230975,35.639275",
            "shopid": [],
            "favorite_num": [],
            "featured_reviews": []
        },
        {
            "parent": [],
            "distance": [],
            "keytag": "幼儿园",
            "importance": [],
            "biz_ext": {
                "cost": [],
                "opentime2": [],
                "rating": [],
                "open_time": []
            },
            "type": "科教文化服务;学校;幼儿园",
            "photos": [
                {
                    "title": [],
                    "url": "http://store.is.autonavi.com/showpic/f9b7026dbcc90fc41ff9c03f928b2e0f"
                },
                {
                    "title": [],
                    "url": "http://store.is.autonavi.com/showpic/8ed8dfd8a7eec91e284ad2ab084a6869"
                },
                {
                    "title": [],
                    "url": "http://store.is.autonavi.com/showpic/f798059df313ed4896081b88fca4c5b7"
                }
            ],
            "building": [],
            "typecode": "141204",
            "shopinfo": "0",
            "poiweight": [],
            "adname": "新绛县",
            "featured_reviews_remake": [],
            "tel": "13753992228",
            "id": "B0FFIB7D2B",
            "address": "荀子路与府西路交叉口西南180米",
            "space_num": [],
            "pname": "山西省",
            "biz_type": [],
            "cityname": "运城市",
            "childtype": [],
            "atag": [],
            "name": "富力城幼儿园",
            "location": "111.218164,35.628532",
            "shopid": [],
            "favorite_num": [],
            "featured_reviews": []
        },
        {
            "parent": [],
            "distance": [],
            "keytag": "小学",
            "importance": [],
            "biz_ext": {
                "cost": [],
                "opentime2": [],
                "rating": [],
                "open_time": []
            },
            "type": "科教文化服务;学校;学校",
            "photos": [
                {
                    "title": [],
                    "url": "http://store.is.autonavi.com/showpic/8cb3664569c79f21f795837540578155"
                },
                {
                    "title": [],
                    "url": "https://store.is.autonavi.com/showpic/c74707735c43d7100000002478264514?type=pic"
                }
            ],
            "building": [],
            "typecode": "141200",
            "shopinfo": "0",
            "poiweight": [],
            "adname": "新绛县",
            "featured_reviews_remake": [],
            "tel": [],
            "id": "B0KD1SE0GA",
            "address": "006乡道",
            "space_num": [],
            "pname": "山西省",
            "biz_type": [],
            "cityname": "运城市",
            "childtype": [],
            "atag": [],
            "name": "西庄学校",
            "location": "111.116592,35.728668",
            "shopid": [],
            "favorite_num": [],
            "featured_reviews": []
        },
        {
            "parent": [],
            "distance": [],
            "keytag": "初级中学",
            "importance": [],
            "biz_ext": {
                "cost": [],
                "opentime2": [],
                "rating": [],
                "open_time": []
            },
            "type": "科教文化服务;学校;学校",
            "photos": [
                {
                    "title": [],
                    "url": "http://store.is.autonavi.com/showpic/d12ffa0efe8320fcd64822dd06cc870e"
                }
            ],
            "building": [],
            "typecode": "141200",
            "shopinfo": "0",
            "poiweight": [],
            "adname": "新绛县",
            "featured_reviews_remake": [],
            "tel": [],
            "id": "B0L65YNLX1",
            "address": "临夏线",
            "space_num": [],
            "pname": "山西省",
            "biz_type": [],
            "cityname": "运城市",
            "childtype": [],
            "atag": [],
            "name": "南苏村学校",
            "location": "111.165899,35.592224",
            "shopid": [],
            "favorite_num": [],
            "featured_reviews": []
        },
        {
            "parent": [],
            "distance": [],
            "keytag": "小学",
            "importance": [],
            "biz_ext": {
                "cost": [],
                "opentime2": [],
                "rating": [],
                "open_time": []
            },
            "type": "科教文化服务;学校;学校",
            "photos": [
                {
                    "title": [],
                    "url": "https://store.is.autonavi.com/showpic/74fdb5e5a15ac05c8e42c8b1062fd71b"
                },
                {
                    "title": [],
                    "url": "http://store.is.autonavi.com/showpic/42b0e6b4542e0de4c7e9a154bec836ac"
                },
                {
                    "title": [],
                    "url": "https://store.is.autonavi.com/showpic/69acd5c193a4a8362f0e71ad911ad2f9"
                }
            ],
            "building": [],
            "typecode": "141200",
            "shopinfo": "0",
            "poiweight": [],
            "adname": "新绛县",
            "featured_reviews_remake": [],
            "tel": [],
            "id": "B0FFHF18U7",
            "address": "泽掌镇",
            "space_num": [],
            "pname": "山西省",
            "biz_type": [],
            "cityname": "运城市",
            "childtype": [],
            "atag": [],
            "name": "乔沟头学校",
            "location": "111.168134,35.769610",
            "shopid": [],
            "favorite_num": [],
            "featured_reviews": []
        },
        {
            "parent": [],
            "distance": [],
            "keytag": "幼儿园",
            "importance": [],
            "biz_ext": {
                "cost": [],
                "opentime2": [],
                "rating": [],
                "open_time": []
            },
            "type": "科教文化服务;学校;幼儿园",
            "photos": [
                {
                    "title": [],
                    "url": "https://store.is.autonavi.com/showpic/b0056ec263c751040000002187192869?type=pic"
                },
                {
                    "title": [],
                    "url": "https://store.is.autonavi.com/showpic/a7a29498445a957055ce20815263a2b9"
                }
            ],
            "building": [],
            "typecode": "141204",
            "shopinfo": "0",
            "poiweight": [],
            "adname": "新绛县",
            "featured_reviews_remake": [],
            "tel": [],
            "id": "B0J3Z7Z7LT",
            "address": "桥北路45号",
            "space_num": [],
            "pname": "山西省",
            "biz_type": [],
            "cityname": "运城市",
            "childtype": [],
            "atag": [],
            "name": "新绛县第二幼儿园",
            "location": "111.227451,35.615068",
            "shopid": [],
            "favorite_num": [],
            "featured_reviews": []
        },
        {
            "parent": [],
            "distance": [],
            "keytag": "幼儿园",
            "importance": [],
            "biz_ext": {
                "cost": [],
                "opentime2": [],
                "rating": [],
                "open_time": []
            },
            "type": "科教文化服务;学校;幼儿园",
            "photos": [
                {
                    "title": [],
                    "url": "http://store.is.autonavi.com/showpic/664028b2898c3359f84e6c535c63bd35"
                }
            ],
            "building": [],
            "typecode": "141204",
            "shopinfo": "0",
            "poiweight": [],
            "adname": "新绛县",
            "featured_reviews_remake": [],
            "tel": [],
            "id": "B0FFHHDAHK",
            "address": "西关路与新北建街交叉口东北120米",
            "space_num": [],
            "pname": "山西省",
            "biz_type": [],
            "cityname": "运城市",
            "childtype": [],
            "atag": [],
            "name": "新绛县幼儿园",
            "location": "111.219742,35.613386",
            "shopid": [],
            "favorite_num": [],
            "featured_reviews": []
        },
        {
            "parent": [],
            "distance": [],
            "keytag": "幼儿园",
            "importance": [],
            "biz_ext": {
                "cost": [],
                "opentime2": [],
                "rating": [],
                "open_time": []
            },
            "type": "科教文化服务;学校;幼儿园",
            "photos": [
                {
                    "title": [],
                    "url": "http://store.is.autonavi.com/showpic/25c78ac357a3c7975e4fd12d6b09c126"
                },
                {
                    "title": [],
                    "url": "http://store.is.autonavi.com/showpic/3db01685b8dcc990921a9da08d0ffc88"
                },
                {
                    "title": [],
                    "url": "http://store.is.autonavi.com/showpic/cacd0031dc7d18b97055c1d5f2a24d6f"
                }
            ],
            "building": [],
            "typecode": "141204",
            "shopinfo": "0",
            "poiweight": [],
            "adname": "新绛县",
            "featured_reviews_remake": [],
            "tel": [],
            "id": "B0GDV56YTM",
            "address": [],
            "space_num": [],
            "pname": "山西省",
            "biz_type": [],
            "cityname": "运城市",
            "childtype": [],
            "atag": [],
            "name": "新纺幼儿园",
            "location": "111.196986,35.589163",
            "shopid": [],
            "favorite_num": [],
            "featured_reviews": []
        },
        {
            "parent": [],
            "distance": [],
            "keytag": "中学",
            "importance": [],
            "biz_ext": {
                "cost": [],
                "opentime2": [],
                "rating": [],
                "open_time": []
            },
            "type": "科教文化服务;学校;中学",
            "photos": [],
            "building": [],
            "typecode": "141202",
            "shopinfo": "0",
            "poiweight": [],
            "adname": "新绛县",
            "featured_reviews_remake": [],
            "tel": [],
            "id": "B0L21RUAVG",
            "address": "正平街与城壕路交叉口东120米",
            "space_num": [],
            "pname": "山西省",
            "biz_type": [],
            "cityname": "运城市",
            "childtype": [],
            "atag": [],
            "name": "老一中",
            "location": "111.219825,35.616975",
            "shopid": [],
            "favorite_num": [],
            "featured_reviews": []
        },
        {
            "parent": [],
            "distance": [],
            "keytag": "科教文化服务,科教文化场所,科教文化场所",
            "importance": [],
            "biz_ext": {
                "cost": [],
                "opentime2": [],
                "rating": "3.9",
                "open_time": []
            },
            "type": "科教文化服务;科教文化场所;科教文化场所",
            "photos": [
                {
                    "title": [],
                    "url": "http://store.is.autonavi.com/showpic/2d3373e9f35f5593b8c70c239a01eeb0"
                }
            ],
            "building": [],
            "typecode": "140000",
            "shopinfo": "0",
            "poiweight": [],
            "adname": "新绛县",
            "featured_reviews_remake": [],
            "tel": [],
            "id": "B0FFKSQ8Y3",
            "address": "龙兴镇富力城步行街",
            "space_num": [],
            "pname": "山西省",
            "biz_type": [],
            "cityname": "运城市",
            "childtype": [],
            "atag": [],
            "name": "星韵艺术培训学校",
            "location": "111.217150,35.627480",
            "shopid": [],
            "favorite_num": [],
            "featured_reviews": []
        }
    ],
    "status": "1",
    "info": "OK"
}